<?xml version="1.0" encoding="UTF-8"?>
<mxGraphModel dx="1422" dy="762" grid="1" gridSize="10" guides="1" tooltips="1" connect="1" arrows="1" fold="1" page="1" pageScale="1" pageWidth="1169" pageHeight="827" math="0" shadow="0">
  <root>
    <mxCell id="0"/>
    <mxCell id="1" parent="0"/>
    <mxCell id="CU_21_Tablero_Metricas_pool" value="CU-21: Admin Revisa Tablero de Métricas de Recaudo" style="swimlane;html=1;horizontal=0;childLayout=stackLayout;horizontalStack=1;resizeParent=1;resizeParentMax=0;startSize=36;fillColor=#ffffff;strokeColor=#000000;fontColor=#000000;fontStyle=1;fontSize=13;swimlaneBackground=#ffffff;collapsible=0;container=1;connectable=0;" vertex="1" parent="1">
      <mxGeometry x="20" y="20" width="516" height="1096" as="geometry"/>
    </mxCell>
    <mxCell id="CU_21_Tablero_Metricas_lane0" value="Admin" style="swimlane;html=1;horizontal=1;startSize=36;fillColor=#ffffff;strokeColor=#000000;fontColor=#000000;fontStyle=1;fontSize=12;swimlaneBackground=#ffffff;collapsible=0;container=1;connectable=0;" vertex="1" parent="CU_21_Tablero_Metricas_pool">
      <mxGeometry x="0" y="0" width="240" height="1096" as="geometry"/>
    </mxCell>
    <mxCell id="CU_21_Tablero_Metricas_lane1" value="Sistema / IA" style="swimlane;html=1;horizontal=1;startSize=36;fillColor=#ffffff;strokeColor=#000000;fontColor=#000000;fontStyle=1;fontSize=12;swimlaneBackground=#ffffff;collapsible=0;container=1;connectable=0;" vertex="1" parent="CU_21_Tablero_Metricas_pool">
      <mxGeometry x="240" y="0" width="240" height="1096" as="geometry"/>
    </mxCell>
    <mxCell id="CU_21_Tablero_Metricas_10" value="" style="ellipse;html=1;fillColor=#ffffff;strokeColor=#000000;strokeWidth=2;verticalLabelPosition=bottom;verticalAlign=top;" vertex="1" parent="CU_21_Tablero_Metricas_lane0">
      <mxGeometry x="108" y="104" width="24" height="24" as="geometry"/>
    </mxCell>
    <mxCell id="CU_21_Tablero_Metricas_11" value="Abre el tablero&#xa;de métricas" style="rounded=1;arcSize=18;whiteSpace=wrap;html=1;fillColor=#ffffff;strokeColor=#000000;fontColor=#000000;align=center;verticalAlign=middle;fontSize=11;strokeWidth=1.2;" vertex="1" parent="CU_21_Tablero_Metricas_lane0">
      <mxGeometry x="30" y="193" width="180" height="46" as="geometry"/>
    </mxCell>
    <mxCell id="CU_21_Tablero_Metricas_12" value="Calcula: tasa, día&#xa;promedio, tendencia" style="rounded=1;arcSize=18;whiteSpace=wrap;html=1;fillColor=#ffffff;strokeColor=#000000;fontColor=#000000;align=center;verticalAlign=middle;fontSize=11;strokeWidth=1.2;" vertex="1" parent="CU_21_Tablero_Metricas_lane1">
      <mxGeometry x="30" y="293" width="180" height="46" as="geometry"/>
    </mxCell>
    <mxCell id="CU_21_Tablero_Metricas_13" value="Muestra desglose&#xa;por sector" style="rounded=1;arcSize=18;whiteSpace=wrap;html=1;fillColor=#ffffff;strokeColor=#000000;fontColor=#000000;align=center;verticalAlign=middle;fontSize=11;strokeWidth=1.2;" vertex="1" parent="CU_21_Tablero_Metricas_lane1">
      <mxGeometry x="30" y="393" width="180" height="46" as="geometry"/>
    </mxCell>
    <mxCell id="CU_21_Tablero_Metricas_14" value="Muestra alertas&#xa;de anomalías (IA)" style="rounded=1;arcSize=18;whiteSpace=wrap;html=1;fillColor=#ffffff;strokeColor=#000000;fontColor=#000000;align=center;verticalAlign=middle;fontSize=11;strokeWidth=1.2;" vertex="1" parent="CU_21_Tablero_Metricas_lane1">
      <mxGeometry x="30" y="493" width="180" height="46" as="geometry"/>
    </mxCell>
    <mxCell id="CU_21_Tablero_Metricas_15" value="Filtra por mes,&#xa;trimestre o año" style="rounded=1;arcSize=18;whiteSpace=wrap;html=1;fillColor=#ffffff;strokeColor=#000000;fontColor=#000000;align=center;verticalAlign=middle;fontSize=11;strokeWidth=1.2;" vertex="1" parent="CU_21_Tablero_Metricas_lane0">
      <mxGeometry x="30" y="593" width="180" height="46" as="geometry"/>
    </mxCell>
    <mxCell id="CU_21_Tablero_Metricas_16" value="Actualiza&#xa;vista filtrada" style="rounded=1;arcSize=18;whiteSpace=wrap;html=1;fillColor=#ffffff;strokeColor=#000000;fontColor=#000000;align=center;verticalAlign=middle;fontSize=11;strokeWidth=1.2;" vertex="1" parent="CU_21_Tablero_Metricas_lane1">
      <mxGeometry x="30" y="693" width="180" height="46" as="geometry"/>
    </mxCell>
    <mxCell id="CU_21_Tablero_Metricas_17" value="Hace clic en sector&#xa;para ver detalle" style="rounded=1;arcSize=18;whiteSpace=wrap;html=1;fillColor=#ffffff;strokeColor=#000000;fontColor=#000000;align=center;verticalAlign=middle;fontSize=11;strokeWidth=1.2;" vertex="1" parent="CU_21_Tablero_Metricas_lane0">
      <mxGeometry x="30" y="793" width="180" height="46" as="geometry"/>
    </mxCell>
    <mxCell id="CU_21_Tablero_Metricas_18" value="Muestra hogares&#xa;del sector" style="rounded=1;arcSize=18;whiteSpace=wrap;html=1;fillColor=#ffffff;strokeColor=#000000;fontColor=#000000;align=center;verticalAlign=middle;fontSize=11;strokeWidth=1.2;" vertex="1" parent="CU_21_Tablero_Metricas_lane1">
      <mxGeometry x="30" y="893" width="180" height="46" as="geometry"/>
    </mxCell>
    <mxCell id="CU_21_Tablero_Metricas_19" value="" style="ellipse;html=1;shape=endState;fillColor=#000000;strokeColor=#000000;strokeWidth=1.2;" vertex="1" parent="CU_21_Tablero_Metricas_lane0">
      <mxGeometry x="108" y="1004" width="24" height="24" as="geometry"/>
    </mxCell>
    <mxCell id="CU_21_Tablero_Metricas_20" value="" style="edgeStyle=orthogonalEdgeStyle;rounded=0;orthogonalLoop=1;jettySize=auto;strokeColor=#000000;strokeWidth=1.2;exitX=0.5;exitY=1;exitDx=0;exitDy=0;entryX=0.5;entryY=0;entryDx=0;entryDy=0;fontSize=10;fontColor=#000000;" edge="1" source="CU_21_Tablero_Metricas_10" target="CU_21_Tablero_Metricas_11" parent="1">
      <mxGeometry relative="1" as="geometry"/>
    </mxCell>
    <mxCell id="CU_21_Tablero_Metricas_21" value="" style="edgeStyle=orthogonalEdgeStyle;rounded=0;orthogonalLoop=1;jettySize=auto;strokeColor=#000000;strokeWidth=1.2;exitX=1;exitY=0.5;exitDx=0;exitDy=0;entryX=0;entryY=0.5;entryDx=0;entryDy=0;fontSize=10;fontColor=#000000;" edge="1" source="CU_21_Tablero_Metricas_11" target="CU_21_Tablero_Metricas_12" parent="1">
      <mxGeometry relative="1" as="geometry"/>
    </mxCell>
    <mxCell id="CU_21_Tablero_Metricas_22" value="" style="edgeStyle=orthogonalEdgeStyle;rounded=0;orthogonalLoop=1;jettySize=auto;strokeColor=#000000;strokeWidth=1.2;exitX=0.5;exitY=1;exitDx=0;exitDy=0;entryX=0.5;entryY=0;entryDx=0;entryDy=0;fontSize=10;fontColor=#000000;" edge="1" source="CU_21_Tablero_Metricas_12" target="CU_21_Tablero_Metricas_13" parent="1">
      <mxGeometry relative="1" as="geometry"/>
    </mxCell>
    <mxCell id="CU_21_Tablero_Metricas_23" value="" style="edgeStyle=orthogonalEdgeStyle;rounded=0;orthogonalLoop=1;jettySize=auto;strokeColor=#000000;strokeWidth=1.2;exitX=0.5;exitY=1;exitDx=0;exitDy=0;entryX=0.5;entryY=0;entryDx=0;entryDy=0;fontSize=10;fontColor=#000000;" edge="1" source="CU_21_Tablero_Metricas_13" target="CU_21_Tablero_Metricas_14" parent="1">
      <mxGeometry relative="1" as="geometry"/>
    </mxCell>
    <mxCell id="CU_21_Tablero_Metricas_24" value="" style="edgeStyle=orthogonalEdgeStyle;rounded=0;orthogonalLoop=1;jettySize=auto;strokeColor=#000000;strokeWidth=1.2;exitX=0;exitY=0.5;exitDx=0;exitDy=0;entryX=1;entryY=0.5;entryDx=0;entryDy=0;fontSize=10;fontColor=#000000;" edge="1" source="CU_21_Tablero_Metricas_14" target="CU_21_Tablero_Metricas_15" parent="1">
      <mxGeometry relative="1" as="geometry"/>
    </mxCell>
    <mxCell id="CU_21_Tablero_Metricas_25" value="" style="edgeStyle=orthogonalEdgeStyle;rounded=0;orthogonalLoop=1;jettySize=auto;strokeColor=#000000;strokeWidth=1.2;exitX=1;exitY=0.5;exitDx=0;exitDy=0;entryX=0;entryY=0.5;entryDx=0;entryDy=0;fontSize=10;fontColor=#000000;" edge="1" source="CU_21_Tablero_Metricas_15" target="CU_21_Tablero_Metricas_16" parent="1">
      <mxGeometry relative="1" as="geometry"/>
    </mxCell>
    <mxCell id="CU_21_Tablero_Metricas_26" value="" style="edgeStyle=orthogonalEdgeStyle;rounded=0;orthogonalLoop=1;jettySize=auto;strokeColor=#000000;strokeWidth=1.2;exitX=0;exitY=0.5;exitDx=0;exitDy=0;entryX=1;entryY=0.5;entryDx=0;entryDy=0;fontSize=10;fontColor=#000000;" edge="1" source="CU_21_Tablero_Metricas_16" target="CU_21_Tablero_Metricas_17" parent="1">
      <mxGeometry relative="1" as="geometry"/>
    </mxCell>
    <mxCell id="CU_21_Tablero_Metricas_27" value="" style="edgeStyle=orthogonalEdgeStyle;rounded=0;orthogonalLoop=1;jettySize=auto;strokeColor=#000000;strokeWidth=1.2;exitX=1;exitY=0.5;exitDx=0;exitDy=0;entryX=0;entryY=0.5;entryDx=0;entryDy=0;fontSize=10;fontColor=#000000;" edge="1" source="CU_21_Tablero_Metricas_17" target="CU_21_Tablero_Metricas_18" parent="1">
      <mxGeometry relative="1" as="geometry"/>
    </mxCell>
    <mxCell id="CU_21_Tablero_Metricas_28" value="" style="edgeStyle=orthogonalEdgeStyle;rounded=0;orthogonalLoop=1;jettySize=auto;strokeColor=#000000;strokeWidth=1.2;exitX=0;exitY=0.5;exitDx=0;exitDy=0;entryX=1;entryY=0.5;entryDx=0;entryDy=0;fontSize=10;fontColor=#000000;" edge="1" source="CU_21_Tablero_Metricas_18" target="CU_21_Tablero_Metricas_19" parent="1">
      <mxGeometry relative="1" as="geometry"/>
    </mxCell>
  </root>
</mxGraphModel>